py_typecheck/__init__.py
py_typecheck/core.py
py_typecheck/py.typed
typecheck_runtime-0.2.0.dist-info/METADATA
typecheck_runtime-0.2.0.dist-info/WHEEL
typecheck_runtime-0.2.0.dist-info/licenses/LICENSE
typecheck_runtime-0.2.0.dist-info/RECORD
