Metadata-Version: 2.4
Name: typecheck-runtime
Version: 0.2.0
Summary: Tiny runtime checker for typing annotations (dict[str,str], list[T], unions, literals) with an Option-like API.
Project-URL: Homepage, https://github.com/schizza/py-typecheck
Project-URL: Repository, https://github.com/schizza/py-typecheck
Project-URL: Issues, https://github.com/schizza/py-typecheck/issues
Author: Lukas Svoboda
License: MIT
License-File: LICENSE
Keywords: runtime,typecheck,typing,validation
Classifier: License :: OSI Approved :: MIT License
Classifier: Programming Language :: Python :: 3
Classifier: Programming Language :: Python :: 3 :: Only
Classifier: Typing :: Typed
Requires-Python: >=3.10
